PyLidar3/__init__.py
PyLidar3-1.6.dist-info/LICENSE
PyLidar3-1.6.dist-info/METADATA
PyLidar3-1.6.dist-info/WHEEL
PyLidar3-1.6.dist-info/top_level.txt
PyLidar3-1.6.dist-info/RECORD
